COPYING
MANIFEST.in
README
README.rst
setup.py
goodruns/__init__.py
goodruns/grl.py
goodruns/info.py
goodruns/sorteddict.py
goodruns.egg-info/PKG-INFO
goodruns.egg-info/SOURCES.txt
goodruns.egg-info/dependency_links.txt
goodruns.egg-info/top_level.txt
goodruns/extern/__init__.py
goodruns/extern/argparse.py
goodruns/tests/__init__.py
goodruns/tests/compare.py
goodruns/tests/tests.py
scripts/grl