Metadata-Version: 1.1
Name: goodruns
Version: 2.8.1
Summary: ATLAS Good Run List (GRL) reader and utilities
Home-page: http://ndawe.github.com/goodruns
Author: Noel Dawe
Author-email: noel.dawe@cern.ch
License: GPLv3
Download-URL: http://pypi.python.org/packages/source/g/goodruns/goodruns-2.8.1.tar.gz
Platform: UNKNOWN
Classifier: Intended Audience :: Science/Research
Classifier: Intended Audience :: Developers
Classifier: Topic :: Software Development
Classifier: Topic :: Scientific/Engineering
Classifier: Topic :: Text Processing :: Markup :: XML
Classifier: Topic :: Utilities
Classifier: Operating System :: POSIX
Classifier: Operating System :: Unix
Classifier: Operating System :: MacOS
Classifier: License :: OSI Approved :: GNU General Public License (GPL)
Classifier: Programming Language :: Python
Classifier: Programming Language :: Python :: 2
Classifier: Development Status :: 5 - Production/Stable
